<Table BorderBrush='Black' BorderThickness='1' TextAlignment='Center' Background='LightGreen'>
   <Table.Columns>
      <TableColumn Width='120'/>
      <TableColumn Width='250'/>
      <TableColumn Width='250'/>
   </Table.Columns>
   <TableRowGroup>
      <TableRow  FontSize='16' >
         <TableCell ColumnSpan='3' TextAlignment='Center' BorderBrush='Black' BorderThickness='1'>
            <Paragraph>
               HE TO KILL (76)
               <LineBreak/>
               <Italic>
                  <Run FontSize='10' Text='Roll the number shown or less to Kill.'></Run>
               </Italic>
            </Paragraph>
         </TableCell>
      </TableRow>
   </TableRowGroup>
   <TableRowGroup>
      <TableRow >
         <TableCell TextAlignment='Left' BorderBrush='Black' BorderThickness='1'>
            <Table>
               <TableRowGroup>
                  <TableRow  FontSize='12' >
                     <TableCell TextAlignment='Center' BorderBrush='LightGreen' BorderThickness='1'>
                        <Paragraph>
                           <Run> </Run>
                        </Paragraph>
                     </TableCell>
                  </TableRow>
                  <TableRow  FontSize='12' >
                     <TableCell TextAlignment='Center' >
                        <Paragraph>
                           <Run Text='Target'></Run>
                        </Paragraph>
                     </TableCell>
                  </TableRow>
                  <TableRow  FontSize='12' >
                     <TableCell TextAlignment='Left' Background='DarkSeaGreen'>
                        <Paragraph>
                           <Run Text='  Pz IV'></Run>
                           <LineBreak/>
                        </Paragraph>
                     </TableCell>
                  </TableRow>
                  <TableRow  FontSize='12' >
                     <TableCell TextAlignment='Left' >
                        <Paragraph>
                           <Run Text='  Pz V'></Run>
                        </Paragraph>
                     </TableCell>
                  </TableRow>
                  <TableRow  FontSize='12' >
                     <TableCell TextAlignment='Left' Background='DarkSeaGreen'>
                        <Paragraph>
                           <Run Text='  Pz VIe'></Run>
                        </Paragraph>
                     </TableCell>
                  </TableRow>
                  <TableRow  FontSize='12' >
                     <TableCell TextAlignment='Left' >
                        <Paragraph>
                           <Run Text='  Pz VIb'></Run>
                           <LineBreak/>
                        </Paragraph>
                     </TableCell>
                  </TableRow>
                  <TableRow  FontSize='12' >
                     <TableCell TextAlignment='Left' Background='DarkSeaGreen'>
                        <Paragraph>
                           <Run Text='  STuG IIIg'></Run>
                        </Paragraph>
                     </TableCell>
                  </TableRow>
                  <TableRow  FontSize='12' >
                     <TableCell TextAlignment='Left' >
                        <Paragraph>
                           <Run Text='  MARDER II'></Run>
                           <LineBreak/>
                        </Paragraph>
                     </TableCell>
                  </TableRow>
                  <TableRow  FontSize='12' >
                     <TableCell TextAlignment='Left' Background='DarkSeaGreen'>
                        <Paragraph>
                           <Run Text='  MARDER III'></Run>
                           <LineBreak/>
                        </Paragraph>
                     </TableCell>
                  </TableRow>
                  <TableRow  FontSize='12' >
                     <TableCell TextAlignment='Left' >
                        <Paragraph>
                           <Run Text='  JgdPz IV'></Run>
                           <LineBreak/>
                        </Paragraph>
                     </TableCell>
                  </TableRow>
                  <TableRow  FontSize='12' >
                     <TableCell TextAlignment='Left' Background='DarkSeaGreen'>
                        <Paragraph>
                           <Run Text='  JgdPz 38t'></Run>
                        </Paragraph>
                     </TableCell>
                  </TableRow>
                  <TableRow  FontSize='12' >
                     <TableCell TextAlignment='Left' >
                        <Paragraph>
                           <Run Text='  PSW, SPW'></Run>
                        </Paragraph>
                     </TableCell>
                  </TableRow>
                  <TableRow  FontSize='12' >
                     <TableCell TextAlignment='Left' Background='DarkSeaGreen'>
                        <Paragraph>
                           <Run Text='  TRUCK'></Run>
                        </Paragraph>
                     </TableCell>
                  </TableRow>
               </TableRowGroup>
            </Table>
         </TableCell>
         <TableCell TextAlignment='Center' BorderBrush='Black' BorderThickness='1'>
            <Table>
               <Table.Columns>
                  <TableColumn Width='80'/>
                  <TableColumn Width='80'/>
                  <TableColumn Width='80'/>
               </Table.Columns>
               <TableRowGroup>
                  <TableRow  FontSize='12' >
                     <TableCell ColumnSpan='3' TextAlignment='Center' BorderBrush='Black' BorderThickness='1'>
                        <Paragraph>
                           <Run>NORMAL HIT</Run>
                        </Paragraph>
                     </TableCell>
                  </TableRow>
                  <TableRow  FontSize='12' >
                     <TableCell TextAlignment='Center' >
                        <Paragraph>
                           <Run Text='Front'></Run>
                        </Paragraph>
                     </TableCell>
                     <TableCell TextAlignment='Center' >
                        <Paragraph>
                           <Run Text='Side'></Run>
                        </Paragraph>
                     </TableCell>
                     <TableCell TextAlignment='Center' >
                        <Paragraph>
                           <Run Text='Rear'></Run>
                        </Paragraph>
                     </TableCell>
                  </TableRow>
                  <!-- Pz IV -->
                  <TableRow  FontSize='12' >
                     <TableCell TextAlignment='Center' Background='DarkSeaGreen'>
                        <Paragraph>
                           <Run Text='nc'></Run>
                           <LineBreak/>
                        </Paragraph>
                     </TableCell>
                     <TableCell TextAlignment='Center' Background='DarkSeaGreen'>
                        <Paragraph>
                           <Run Text='nc'></Run>
                           <LineBreak/>
                        </Paragraph>
                     </TableCell>
                     <TableCell TextAlignment='Center' Background='DarkSeaGreen'>
                        <Paragraph>
                           <Run Text='T nc'></Run>
                           <LineBreak/>
                           <Run Text='H 02'></Run>
                        </Paragraph>
                     </TableCell>
                  </TableRow>
                  <!-- Pz V -->
                  <TableRow  FontSize='12' >
                     <TableCell TextAlignment='Center'>
                        <Paragraph>
                           <Run Text='nc'></Run>
                        </Paragraph>
                     </TableCell>
                     <TableCell TextAlignment='Center'>
                        <Paragraph>
                           <Run Text='nc'></Run>
                        </Paragraph>
                     </TableCell>
                     <TableCell TextAlignment='Center' >
                        <Paragraph>
                           <Run Text='nc'></Run>
                        </Paragraph>
                     </TableCell>
                  </TableRow>
                  <!-- Pz VIe -->
                  <TableRow  FontSize='12' >
                     <TableCell TextAlignment='Center' Background='DarkSeaGreen'>
                        <Paragraph>
                           <Run Text='nc'></Run>
                        </Paragraph>
                     </TableCell>
                     <TableCell TextAlignment='Center' Background='DarkSeaGreen'>
                        <Paragraph>
                           <Run Text='nc'></Run>
                        </Paragraph>
                     </TableCell>
                     <TableCell TextAlignment='Center' Background='DarkSeaGreen'>
                        <Paragraph>
                           <Run Text='nc'></Run>
                        </Paragraph>
                     </TableCell>
                  </TableRow>
                  <!-- Pz VIb -->
                  <TableRow  FontSize='12' >
                     <TableCell TextAlignment='Center'>
                        <Paragraph>
                           <Run Text='nc'></Run>
                           <LineBreak/>
                        </Paragraph>
                     </TableCell>
                     <TableCell TextAlignment='Center'>
                        <Paragraph>
                           <Run Text='nc'></Run>
                           <LineBreak/>
                        </Paragraph>
                     </TableCell>
                     <TableCell TextAlignment='Center' >
                        <Paragraph>
                           <Run Text='nc'></Run>
                           <LineBreak/>
                        </Paragraph>
                     </TableCell>
                  </TableRow>
                  <!-- STuG IIIg -->
                  <TableRow  FontSize='12' >
                     <TableCell TextAlignment='Center' Background='DarkSeaGreen'>
                        <Paragraph>
                           <Run Text='nc'></Run>
                        </Paragraph>
                     </TableCell>
                     <TableCell TextAlignment='Center' Background='DarkSeaGreen'>
                        <Paragraph>
                           <Run Text='nc'></Run>
                        </Paragraph>
                     </TableCell>
                     <TableCell TextAlignment='Center' Background='DarkSeaGreen'>
                        <Paragraph>
                           <Run Text='02'></Run>
                        </Paragraph>
                     </TableCell>
                  </TableRow>
                  <!-- MARDER II -->
                  <TableRow  FontSize='12' >
                     <TableCell TextAlignment='Center'>
                        <Paragraph>
                           <Run Text='T 02'></Run>
                           <LineBreak/>
                           <Run Text='H nc'></Run>
                        </Paragraph>
                     </TableCell>
                     <TableCell TextAlignment='Center'>
                        <Paragraph>
                           <Run Text='T 27'></Run>
                           <LineBreak/>
                           <Run Text='H 13'></Run>
                        </Paragraph>
                     </TableCell>
                     <TableCell TextAlignment='Center' >
                        <Paragraph>
                           <Run Text='T 43'></Run>
                           <LineBreak/>
                           <Run Text='H 27'></Run>
                        </Paragraph>
                     </TableCell>
                  </TableRow>
                  <!-- MARDER III -->
                  <TableRow  FontSize='12' >
                     <TableCell TextAlignment='Center' Background='DarkSeaGreen'>
                        <Paragraph>
                           <Run Text='T 13'></Run>
                           <LineBreak/>
                           <Run Text='H 02'></Run>
                        </Paragraph>
                     </TableCell>
                     <TableCell TextAlignment='Center' Background='DarkSeaGreen'>
                        <Paragraph>
                           <Run Text='T 27'></Run>
                           <LineBreak/>
                           <Run Text='H 13'></Run>
                        </Paragraph>
                     </TableCell>
                     <TableCell TextAlignment='Center' Background='DarkSeaGreen'>
                        <Paragraph>
                           <Run Text='T 43'></Run>
                           <LineBreak/>
                           <Run Text='H 27'></Run>
                        </Paragraph>
                     </TableCell>
                  </TableRow>
                  <!-- JgdPz IV -->
                  <TableRow  FontSize='12' >
                     <TableCell TextAlignment='Center'>
                        <Paragraph>
                           <Run Text='nc'></Run>
                           <LineBreak/>
                        </Paragraph>
                     </TableCell>
                     <TableCell TextAlignment='Center'>
                        <Paragraph>
                           <Run Text='nc'></Run>
                           <LineBreak/>
                        </Paragraph>
                     </TableCell>
                     <TableCell TextAlignment='Center' >
                        <Paragraph>
                           <Run Text='T nc'></Run>
                           <LineBreak/>
                           <Run Text='H 02'></Run>
                        </Paragraph>
                     </TableCell>
                  </TableRow>
                  <!-- JgdPz 38t -->
                  <TableRow  FontSize='12' >
                     <TableCell TextAlignment='Center' Background='DarkSeaGreen'>
                        <Paragraph>
                           <Run Text='nc'></Run>
                        </Paragraph>
                     </TableCell>
                     <TableCell TextAlignment='Center' Background='DarkSeaGreen'>
                        <Paragraph>
                           <Run Text='02'></Run>
                        </Paragraph>
                     </TableCell>
                     <TableCell TextAlignment='Center' Background='DarkSeaGreen'>
                        <Paragraph>
                           <Run Text='02'></Run>
                        </Paragraph>
                     </TableCell>
                  </TableRow>
                  <!-- PSW, SPW -->
                  <TableRow  FontSize='12' >
                     <TableCell TextAlignment='Center'  >
                        <Paragraph>
                           <Run Text='13'></Run>
                        </Paragraph>
                     </TableCell>
                     <TableCell TextAlignment='Center'  >
                        <Paragraph>
                           <Run Text='13'></Run>
                        </Paragraph>
                     </TableCell>
                     <TableCell TextAlignment='Center'  >
                        <Paragraph>
                           <Run Text='27'></Run>
                        </Paragraph>
                     </TableCell>
                  </TableRow>
                  <!-- TRUCK -->
                  <TableRow  FontSize='12' >
                     <TableCell TextAlignment='Center' Background='DarkSeaGreen'>
                        <Paragraph>
                           <Run Text='95'></Run>
                        </Paragraph>
                     </TableCell>
                     <TableCell TextAlignment='Center' Background='DarkSeaGreen'>
                        <Paragraph>
                           <Run Text='95'></Run>
                        </Paragraph>
                     </TableCell>
                     <TableCell TextAlignment='Center' Background='DarkSeaGreen'>
                        <Paragraph>
                           <Run Text='95'></Run>
                        </Paragraph>
                     </TableCell>
                  </TableRow>
               </TableRowGroup>
            </Table>
         </TableCell>
         <TableCell TextAlignment='Center' BorderBrush='Black' BorderThickness='1'>
            <Table>
               <Table.Columns>
                  <TableColumn Width='80'/>
                  <TableColumn Width='80'/>
                  <TableColumn Width='80'/>
               </Table.Columns>
               <TableRowGroup>
                  <TableRow  FontSize='12' >
                     <TableCell ColumnSpan='3' TextAlignment='Center' BorderBrush='Black' BorderThickness='1'>
                        <Paragraph>
                           <Run>CRITICAL HIT</Run>
                        </Paragraph>
                     </TableCell>
                  </TableRow>
                  <TableRow  FontSize='12' >
                     <TableCell TextAlignment='Center' >
                        <Paragraph>
                           <Run Text='Front'></Run>
                        </Paragraph>
                     </TableCell>
                     <TableCell TextAlignment='Center' >
                        <Paragraph>
                           <Run Text='Side'></Run>
                        </Paragraph>
                     </TableCell>
                     <TableCell TextAlignment='Center' >
                        <Paragraph>
                           <Run Text='Rear'></Run>
                        </Paragraph>
                     </TableCell>
                  </TableRow>
                  <!-- Pz IV -->
                  <TableRow  FontSize='12' >
                     <TableCell TextAlignment='Center' Background='DarkSeaGreen'>
                        <Paragraph>
                           <Run Text='T 43'></Run>
                           <LineBreak/>
                           <Run Text='H 27'></Run>
                        </Paragraph>
                     </TableCell>
                     <TableCell TextAlignment='Center' Background='DarkSeaGreen'>
                        <Paragraph>
                           <Run Text='T 68'></Run>
                           <LineBreak/>
                           <Run Text='H 77'></Run>
                        </Paragraph>
                     </TableCell>
                     <TableCell TextAlignment='Center' Background='DarkSeaGreen'>
                        <Paragraph>
                           <Run Text='T 77'></Run>
                           <LineBreak/>
                           <Run Text='H 82'></Run>
                        </Paragraph>
                     </TableCell>
                  </TableRow>
                  <!-- Pz V -->
                  <TableRow  FontSize='12' >
                     <TableCell TextAlignment='Center'>
                        <Paragraph>
                           <Run Text='nc'></Run>
                        </Paragraph>
                     </TableCell>
                     <TableCell TextAlignment='Center'>
                        <Paragraph>
                           <Run Text='43'></Run>
                        </Paragraph>
                     </TableCell>
                     <TableCell TextAlignment='Center' >
                        <Paragraph>
                           <Run Text='57'></Run>
                        </Paragraph>
                     </TableCell>
                  </TableRow>
                  <!-- Pz VIe -->
                  <TableRow  FontSize='12' >
                     <TableCell TextAlignment='Center' Background='DarkSeaGreen'>
                        <Paragraph>
                           <Run Text='nc'></Run>
                        </Paragraph>
                     </TableCell>
                     <TableCell TextAlignment='Center' Background='DarkSeaGreen'>
                        <Paragraph>
                           <Run Text='13'></Run>
                        </Paragraph>
                     </TableCell>
                     <TableCell TextAlignment='Center' Background='DarkSeaGreen'>
                        <Paragraph>
                           <Run Text='27'></Run>
                        </Paragraph>
                     </TableCell>
                  </TableRow>
                  <!-- Pz VIb -->
                  <TableRow  FontSize='12' >
                     <TableCell TextAlignment='Center'>
                        <Paragraph>
                           <Run Text='nc'></Run>
                           <LineBreak/>
                           <Run Text=''></Run>
                        </Paragraph>
                     </TableCell>
                     <TableCell TextAlignment='Center'>
                        <Paragraph>
                           <Run Text='nc'></Run>
                           <LineBreak/>
                           <Run Text='H 13'></Run>
                        </Paragraph>
                     </TableCell>
                     <TableCell TextAlignment='Center' >
                        <Paragraph>
                           <Run Text='T nc'></Run>
                           <LineBreak/>
                           <Run Text='H 27'></Run>
                        </Paragraph>
                     </TableCell>
                  </TableRow>
                  <!-- STuG IIIg -->
                  <TableRow  FontSize='12' >
                     <TableCell TextAlignment='Center' Background='DarkSeaGreen'>
                        <Paragraph>
                           <Run Text='13'></Run>
                        </Paragraph>
                     </TableCell>
                     <TableCell TextAlignment='Center' Background='DarkSeaGreen'>
                        <Paragraph>
                           <Run Text='77'></Run>
                        </Paragraph>
                     </TableCell>
                     <TableCell TextAlignment='Center' Background='DarkSeaGreen'>
                        <Paragraph>
                           <Run Text='82'></Run>
                        </Paragraph>
                     </TableCell>
                  </TableRow>
                  <!-- MARDER II -->
                  <TableRow  FontSize='12' >
                     <TableCell TextAlignment='Center'>
                        <Paragraph>
                           <Run Text='T 82'></Run>
                           <LineBreak/>
                           <Run Text='H 77'></Run>
                        </Paragraph>
                     </TableCell>
                     <TableCell TextAlignment='Center'>
                        <Paragraph>
                           <Run Text='100'></Run>
                           <LineBreak/>
                        </Paragraph>
                     </TableCell>
                     <TableCell TextAlignment='Center' >
                        <Paragraph>
                           <Run Text='100'></Run>
                           <LineBreak/>
                        </Paragraph>
                     </TableCell>
                  </TableRow>
                  <!-- MARDER III -->
                  <TableRow  FontSize='12' >
                     <TableCell TextAlignment='Center' Background='DarkSeaGreen'>
                        <Paragraph>
                           <Run Text='T 100'></Run>
                           <LineBreak/>
                           <Run Text='H 82'></Run>
                        </Paragraph>
                     </TableCell>
                     <TableCell TextAlignment='Center' Background='DarkSeaGreen'>
                        <Paragraph>
                           <Run Text='100'></Run>
                           <LineBreak/>
                        </Paragraph>
                     </TableCell>
                     <TableCell TextAlignment='Center' Background='DarkSeaGreen'>
                        <Paragraph>
                           <Run Text='100'></Run>
                           <LineBreak/>
                        </Paragraph>
                     </TableCell>
                  </TableRow>
                  <!-- JgdPz IV -->
                  <TableRow  FontSize='12' >
                     <TableCell TextAlignment='Center'>
                        <Paragraph>
                           <Run Text='nc'></Run>
                           <LineBreak/>
                        </Paragraph>
                     </TableCell>
                     <TableCell TextAlignment='Center'>
                        <Paragraph>
                           <Run Text='T 67'></Run>
                           <LineBreak/>
                           <Run Text='H 77'></Run>
                        </Paragraph>
                     </TableCell>
                     <TableCell TextAlignment='Center' >
                        <Paragraph>
                           <Run Text='T 77'></Run>
                           <LineBreak/>
                           <Run Text='H 82'></Run>
                        </Paragraph>
                     </TableCell>
                  </TableRow>
                  <!-- JgdPz 38t -->
                  <TableRow  FontSize='12' >
                     <TableCell TextAlignment='Center' Background='DarkSeaGreen'>
                        <Paragraph>
                           <Run Text='nc'></Run>
                        </Paragraph>
                     </TableCell>
                     <TableCell TextAlignment='Center' Background='DarkSeaGreen'>
                        <Paragraph>
                           <Run Text='77'></Run>
                        </Paragraph>
                     </TableCell>
                     <TableCell TextAlignment='Center' Background='DarkSeaGreen'>
                        <Paragraph>
                           <Run Text='82'></Run>
                        </Paragraph>
                     </TableCell>
                  </TableRow>
                  <!-- PSW, SPW -->
                  <TableRow  FontSize='12' >
                     <TableCell TextAlignment='Center'  >
                        <Paragraph>
                           <Run Text='100'></Run>
                        </Paragraph>
                     </TableCell>
                     <TableCell TextAlignment='Center'  >
                        <Paragraph>
                           <Run Text='100'></Run>
                        </Paragraph>
                     </TableCell>
                     <TableCell TextAlignment='Center'  >
                        <Paragraph>
                           <Run Text='100'></Run>
                        </Paragraph>
                     </TableCell>
                  </TableRow>
                  <!-- TRUCK -->
                  <TableRow  FontSize='12' >
                     <TableCell TextAlignment='Center' Background='DarkSeaGreen'>
                        <Paragraph>
                           <Run Text='100'></Run>
                        </Paragraph>
                     </TableCell>
                     <TableCell TextAlignment='Center' Background='DarkSeaGreen'>
                        <Paragraph>
                           <Run Text='100'></Run>
                        </Paragraph>
                     </TableCell>
                     <TableCell TextAlignment='Center' Background='DarkSeaGreen'>
                        <Paragraph>
                           <Run Text='100'></Run>
                        </Paragraph>
                     </TableCell>
                  </TableRow>
               </TableRowGroup>
            </Table>
         </TableCell>
      </TableRow>
   </TableRowGroup>
   <TableRowGroup>
      <TableRow  FontSize='12' >
         <TableCell ColumnSpan='3' TextAlignment='Left' BorderBrush='Black' BorderThickness='1'>
            <Paragraph>
               <Run>  NOTES:</Run>
               <LineBreak/>
               <Run Text='   (1) T = Turret, H = Hull, nc = no chance'></Run>
            </Paragraph>
         </TableCell>
      </TableRow>
   </TableRowGroup>
</Table>